TextEncoder-0.1.0.dist-info/DESCRIPTION.rst
TextEncoder-0.1.0.dist-info/METADATA
TextEncoder-0.1.0.dist-info/RECORD
TextEncoder-0.1.0.dist-info/WHEEL
TextEncoder-0.1.0.dist-info/metadata.json
TextEncoder-0.1.0.dist-info/top_level.txt
encoder/__init__.py
encoder/transformer.py
