Metadata-Version: 1.0
Name: TextEncoder
Version: 0.1.0
Summary: text encoder
Home-page: https://github.com/Lzejie/TextEncoder
Author: L_zejie
Author-email: lzj_xuexi@163.com
License: MIT Licence
Keywords: text,encoder,nlp
Platform: UNKNOWN
